LICENSE
oshi/__init__.py
oshi/auth.py
oshi/client.py
oshi/http.py
oshi/objects/__init__.py
oshi/objects/base.py
oshi/objects/beatmap.py
oshi/utils.py
oshi-0.1.0.dist-info/LICENSE
oshi-0.1.0.dist-info/WHEEL
oshi-0.1.0.dist-info/METADATA
oshi-0.1.0.dist-info/RECORD
